Metadata-Version: 2.1
Name: recdoll
Version: 0.0.2
Summary: Best Recommendation Library
Home-page: https://github.com/daun4168/recdoll
Download-URL: https://github.com/daun4168/recdoll/archive/v0.0.2.tar.gz
Author: Daun Jeong
Author-email: daun.jeong@navercorp.com
License: MIT
Keywords: Recommendation,Machine Learning
Platform: UNKNOWN
Classifier: Development Status :: 3 - Alpha
Classifier: Intended Audience :: Developers
Classifier: License :: OSI Approved :: MIT License
Classifier: Programming Language :: Python :: 3
Classifier: Programming Language :: Python :: 3.9
License-File: LICENSE.txt
